flixtube_common/__init__.py
flixtube_common/cosmosdb/__init__.py
flixtube_common/cosmosdb/db_operations.py
flixtube_common/rabbitmq/__init__.py
flixtube_common/rabbitmq/pika_client.py
flixtube_common-0.0.10.dist-info/METADATA
flixtube_common-0.0.10.dist-info/WHEEL
flixtube_common-0.0.10.dist-info/top_level.txt
flixtube_common-0.0.10.dist-info/RECORD
